odoo9_addon_account_invoice_currency-9.0.1.0.0-py2.7-nspkg.pth
odoo9_addon_account_invoice_currency-9.0.1.0.0.dist-info/top_level.txt
odoo9_addon_account_invoice_currency-9.0.1.0.0.dist-info/WHEEL
odoo9_addon_account_invoice_currency-9.0.1.0.0.dist-info/RECORD
odoo9_addon_account_invoice_currency-9.0.1.0.0.dist-info/metadata.json
odoo9_addon_account_invoice_currency-9.0.1.0.0.dist-info/DESCRIPTION.rst
odoo9_addon_account_invoice_currency-9.0.1.0.0.dist-info/METADATA
odoo9_addon_account_invoice_currency-9.0.1.0.0.dist-info/namespace_packages.txt
odoo_addons/account_invoice_currency/__openerp__.py
odoo_addons/account_invoice_currency/__init__.py
odoo_addons/account_invoice_currency/README.rst
odoo_addons/account_invoice_currency/migrations/9.0.1.0.0/pre-migrate.py
odoo_addons/account_invoice_currency/models/account_invoice.py
odoo_addons/account_invoice_currency/models/__init__.py
odoo_addons/account_invoice_currency/i18n/ja.po
odoo_addons/account_invoice_currency/i18n/zh_CN.po
odoo_addons/account_invoice_currency/i18n/account_invoice_currency.pot
odoo_addons/account_invoice_currency/i18n/ru.po
odoo_addons/account_invoice_currency/i18n/pt.po
odoo_addons/account_invoice_currency/i18n/it.po
odoo_addons/account_invoice_currency/i18n/es.po
odoo_addons/account_invoice_currency/i18n/nl_BE.po
odoo_addons/account_invoice_currency/i18n/ar.po
odoo_addons/account_invoice_currency/i18n/lt.po
odoo_addons/account_invoice_currency/i18n/ro.po
odoo_addons/account_invoice_currency/i18n/tr.po
odoo_addons/account_invoice_currency/i18n/mk.po
odoo_addons/account_invoice_currency/i18n/hr.po
odoo_addons/account_invoice_currency/i18n/es_EC.po
odoo_addons/account_invoice_currency/i18n/zh_TW.po
odoo_addons/account_invoice_currency/i18n/hu.po
odoo_addons/account_invoice_currency/i18n/ca.po
odoo_addons/account_invoice_currency/i18n/id.po
odoo_addons/account_invoice_currency/i18n/es_CR.po
odoo_addons/account_invoice_currency/i18n/sl.po
odoo_addons/account_invoice_currency/i18n/th.po
odoo_addons/account_invoice_currency/i18n/cs.po
odoo_addons/account_invoice_currency/i18n/nb.po
odoo_addons/account_invoice_currency/i18n/et.po
odoo_addons/account_invoice_currency/i18n/mn.po
odoo_addons/account_invoice_currency/i18n/nl.po
odoo_addons/account_invoice_currency/i18n/de.po
odoo_addons/account_invoice_currency/i18n/fr.po
odoo_addons/account_invoice_currency/i18n/pl.po
odoo_addons/account_invoice_currency/i18n/bs.po
